pynecraft/__init__.py
pynecraft/base.py
pynecraft/commands.py
pynecraft/enums.py
pynecraft/function.py
pynecraft/info.py
pynecraft/menus.py
pynecraft/simpler.py
pynecraft/_utils/build_enums.py
pynecraft/_utils/fetch_things.py
pynecraft-0.7.dist-info/LICENSE
pynecraft-0.7.dist-info/METADATA
pynecraft-0.7.dist-info/WHEEL
pynecraft-0.7.dist-info/top_level.txt
pynecraft-0.7.dist-info/RECORD
